flakytest/__about__.py
flakytest/__init__.py
flakytest/env_vars.py
flakytest/hook.py
flakytest-2023.0b11.dist-info/METADATA
flakytest-2023.0b11.dist-info/WHEEL
flakytest-2023.0b11.dist-info/entry_points.txt
flakytest-2023.0b11.dist-info/licenses/LICENSE.txt
flakytest-2023.0b11.dist-info/RECORD
